harlanbot/__init__.py
harlanbot/chatbot.py
harlanbot/intents.json
harlanbot-0.1.2.dist-info/METADATA
harlanbot-0.1.2.dist-info/WHEEL
harlanbot-0.1.2.dist-info/top_level.txt
harlanbot-0.1.2.dist-info/RECORD
