Metadata-Version: 2.1
Name: harlanbot
Version: 0.1.2
Summary: Create your own custom chatbot
Home-page: https://github.com/harlansr/harlanbot
Author: HarlanSR
Requires-Dist: nltk
Requires-Dist: tensorflow
Requires-Dist: pillow==9.5.0
